p_config/__init__.py
p_config/converter.py
p_config/core.py
p_config/utils.py
tests/__init__.py
tests/default.yml
tests/override.yml
tests/test_p_config.py
p_config-1.4.0.dist-info/AUTHORS.rst
p_config-1.4.0.dist-info/LICENSE
p_config-1.4.0.dist-info/METADATA
p_config-1.4.0.dist-info/WHEEL
p_config-1.4.0.dist-info/top_level.txt
p_config-1.4.0.dist-info/RECORD
