Metadata-Version: 2.1
Name: p-config
Version: 1.4.0
Summary: small tool for project config management
Home-page: UNKNOWN
Author: Abraham
Author-email: abraham.liu@hotmail.com
License: BSD
Project-URL: Source Code, https://github.com/zlqm/p_config
Project-URL: Issue Tracker, https://github.com/zlqm/p_config/issues/
Platform: UNKNOWN
Classifier: Development Status :: 5 - Production/Stable
Classifier: Intended Audience :: Developers
Classifier: Intended Audience :: System Administrators
Classifier: Operating System :: OS Independent
Classifier: Programming Language :: Python
Classifier: Topic :: Utilities
Requires-Python: >=3.6
Requires-Dist: PyYAML
